automon/__init__.py
automon/healthcheck.py
automon/liveliness.py
automon/helpers/__init__.py
automon/helpers/assertions.py
automon/helpers/dates.py
automon/helpers/httpWrapper.py
automon/helpers/markdown.py
automon/helpers/networking.py
automon/helpers/regex.py
automon/helpers/sanitation.py
automon/helpers/sleeper.py
automon/helpers/asyncioWrapper/__init__.py
automon/helpers/asyncioWrapper/loop.py
automon/helpers/cProfileWrapper/__init__.py
automon/helpers/cryptography/__init__.py
automon/helpers/cryptography/hashing.py
automon/helpers/cryptography/secret.py
automon/helpers/debug/__init__.py
automon/helpers/dictWrapper/__init__.py
automon/helpers/jsonWrapper/__init__.py
automon/helpers/loggingWrapper/__init__.py
automon/helpers/loggingWrapper/attributes.py
automon/helpers/loggingWrapper/callback.py
automon/helpers/loggingWrapper/client.py
automon/helpers/loggingWrapper/extended.py
automon/helpers/loggingWrapper/handler.py
automon/helpers/loggingWrapper/stream.py
automon/helpers/loggingWrapper/util.py
automon/helpers/loggingWrapper/tests/__init__.py
automon/helpers/loggingWrapper/tests/test_client.py
automon/helpers/loggingWrapper/tests/test_log_secret.py
automon/helpers/loggingWrapper/tests/test_logger_builtin.py
automon/helpers/mathWrapper/__init__.py
automon/helpers/mathWrapper/file_size.py
automon/helpers/osWrapper/__init__.py
automon/helpers/osWrapper/environ.py
automon/helpers/subprocessWrapper/__init__.py
automon/helpers/subprocessWrapper/exceptions.py
automon/helpers/subprocessWrapper/run.py
automon/helpers/subprocessWrapper/tests/__init__.py
automon/helpers/subprocessWrapper/tests/test_run.py
automon/helpers/subprocessWrapper/tests/test_runner.py
automon/helpers/subprocessWrapper/tests/test_sanitize.py
automon/helpers/subprocessWrapper/tests/test_text.py
automon/helpers/tempfileWrapper/__init__.py
automon/helpers/tests/__init__.py
automon/helpers/tests/test_assertions.py
automon/helpers/tests/test_healthcheck.py
automon/helpers/tests/test_helpers.py
automonisaur-0.6.23.dist-info/METADATA
automonisaur-0.6.23.dist-info/WHEEL
automonisaur-0.6.23.dist-info/top_level.txt
automonisaur-0.6.23.dist-info/RECORD
