Metadata-Version: 2.1
Name: automonisaur
Version: 0.6.23
Summary: Core libraries for automonisaur
Home-page: https://github.com/TheShellLand/automonisaur
Author: naisanza
Author-email: naisanza@gmail.com
Classifier: Programming Language :: Python :: 3
Classifier: Operating System :: OS Independent
Classifier: License :: OSI Approved :: GNU General Public License v3 (GPLv3)
Requires-Python: >=3.10
